{
  "comments": [
    {
      "id": "UgybznjF9wa7qFfKXIN4AaABAg",
      "parent": "root",
      "text": "00:00 - у программы нет мотивации работать более эффективно\r\n05:55 - про этику и отсылка к книге Г.Гаррисона \"Специалист по этике\"\r\n06:33 - про системы, затрагивающие жизнь людей\r\n08:47 - Юваль Харари: \"Машина знает нас лучше, чем мы сами\"\r\n09:40 - Роберт Шекли многое предвосхитил\r\n10:37 - разница все же есть\r\n11:30 - Антон Сабуров: \"ИИ не принесет много вреда\"\r\n12:19 - об ответственности за действия в различных профессиях \r\n15:14 - о закладке некоторого процента ошибок\r\n18:00 - система сдержек и противовесов\r\n19:00 - о конкуренции - отсылка к к/ф \"Куб\"\r\n21:00 - Антон Сабуров: \"Не надо пытаться внедрить ИИ во все места..\"\r\n22:30 - Анча о своем опыте встречи с оптимизацией процесса\r\n27:19 - Антон: \"Это решение не ИИ, это решение человека\"\r\n28:48 - о нарушении прав конкретных групп\r\n30:52 - жизнь усложняется - экономия на безопасности\r\n33:51 - о промежутках внимания \r\n35:46 - Из Гёте: нет ленивых людей - есть неинтересные цели\r\n39:30 - о системе перебора на примере шахмат\r\n42:27 - предложение продолжить обсуждение",
      "author_id": "UCdZcJ0akX0dTD9lSJTbjG_g",
      "author": "@dina-n9005",
      "author_thumbnail": "https://yt3.ggpht.com/ytc/AIdro_lGEkFpJZmZniNT5g38Bipo3CiNCqgbGo7aP1c4u0DPhiY=s88-c-k-c0x00ffffff-no-rj",
      "author_is_uploader": false,
      "author_is_verified": false,
      "author_url": "https://www.youtube.com/@dina-n9005",
      "is_favorited": false,
      "is_pinned": true
    }
  ]
}
