{
  "comments": [
    {
      "id": "UgzqLxtms-wd7k5Sg7Z4AaABAg",
      "parent": "root",
      "text": "Тайм-коды (👇🏻 - в подкомментариях):",
      "author_id": "UCUv2d26BIwPdADOPWJNWtCA",
      "author": "@tatiyana8934",
      "author_thumbnail": "https://yt3.ggpht.com/ytc/AIdro_mXI8-EOUqSNpx0og7DpiBLxSD_mIUjw4493KhYLlyDdS0=s88-c-k-c0x00ffffff-no-rj",
      "author_is_uploader": false,
      "author_is_verified": false,
      "author_url": "https://www.youtube.com/@tatiyana8934",
      "is_favorited": false,
      "is_pinned": true
    },
    {
      "id": "UgzqLxtms-wd7k5Sg7Z4AaABAg.9nPdEjDPmvv9nPdI8hs03z",
      "parent": "UgzqLxtms-wd7k5Sg7Z4AaABAg",
      "text": "тайм-коды - первая половинка:\n00:01  Перезапуск стрима!)) \n00:29  нет ли информации в мед.источниках - нужно ли при приёме статинов \nподдерживать постоянный уровень в крови? \n- Можно ли делать приём 10мг Крестора через день из-за судорог ног? \n\n01:32 что лучше:NMN или Q10? - или можно их принимать одновременно?\n\n02:09 может ли быть постоянный шум в голове из-за некомпенсированного гипотиреоза?\n\n02:31  Паксловид нельзя одновременно с Эликвисом - Вы говорили, \n- а как-же быть с антикоагулянтами?? \n\n02:53  дочь 9 лет с лета болеет ОРИ уже 9-й раз за 9 мес с кашлем.\n Были у иммунолога, по расширенной иммунограмме со слов врача все в относительной норме, \nтолько снижен общий IgA. Назначен Бронхо-мунал. -? \n\n03:32  (@Julia) - Спасибо большое! Это у моего отца 82 года!\n Куча сердечной патологии и последняя операция по резекции аневризмы аорты. \nУ него реакция на статины в виде судорог... \n\n03:45  как ещё повысить IgA? \n\n03:55  Добавить лайки!!! 🌟 👍🏻 \n\n04:08  💚✨ - посильная поддержка канала сообществом! - Большое Спасибо!!! \n\n04:15  что Вы думаете про препарат железа Ферлатум? \nОчень тяжело переносится, к сожалению, как помочь? - Благодарю!🌹\n\n04:42  (Висим?) - Не висим!!!\n\n05:49  отчего воспаляется лимфоузел на шее сзади - в волосяном покрове. - ? \n\n06:19  дк-тр Берг сообщил, что витамины В химически вредные, \nа надо пить натуральные. Что Вы думаете?\n\n07:07  может ли недостаток витамина С ( 20, норма от 40) вызвать ломкость капилляров?\n Спасибо!💚\n\n​07:23  Анча, верите ли Вы в гороскопы?, и кто Вы по гороскопу?\n\n​08:36  если немеет левая сторона лица, с чего начать обследование?\n\n08:52  подскажите, как и где сделать секвенирование экзома,\n если нет никаких намётков на диагноз, и неврологи\n отказываются дать результаты наблюдения или выставить диагноз хотя бы. -?\n\n09:39  вместо Ферлатум, услышала Феринжект и Моноферикум, \nне нашла второе, не так пишется?\n( - Монофер👌🏻) \n\n09:53  может ли постоянный шум в голове быть из-за некомпенсированного гипотиреоза?... \n\n10:38  мне гематолог говорила после 500мг феринжекта \nчерез 2 мес сделать анализ, и через 6 мес по анализу принимать мальтофер - раньше не понадобится. \nМне на год хватило... \n\n11:08  местные врачи при остеопорозе предлагают или Акласту или Пролиа, \n-типа, на ваш выбор. Очень ждём стрим по остеопорозу с Ю.Потешкиным, \nчтобы выбрать пограмотнее\n\n11:33   1,5 месяца назад ковид в лёгкой форме (насморк 1,5 дня) тест домашний. \n10 дней назад гипертонический криз, сейчас СОЭ 51, остальные показатели крови почти в норме,\n ЭКГ норма.Стоит беспокоиться?\n\n12:07  какую дозу Феринжекта принимала Анча \n\n12:16  в какой лекарственной форме лучше искать селен?\n\n12:28  скажите пожалуйста, как вывести песок из почек? \n\n12:51  напомните пож, какие продвинутые анализы сделать при гиперхолестеринемии \nчтобы определить необходимы ли статины (кроме развернутой липидогоаммы) ?\n\n13:26  можно сорбифер дурулес применять 8мес по 1таб? \n- без них плохо чувствую, низкие железо и ферритин, или пора менять препарат? \n\n13:48  про стаканы из Икеи... \n\n14:41  моноферик/феринжект\n...",
      "author_id": "UCUv2d26BIwPdADOPWJNWtCA",
      "author": "@tatiyana8934",
      "author_thumbnail": "https://yt3.ggpht.com/ytc/AIdro_mXI8-EOUqSNpx0og7DpiBLxSD_mIUjw4493KhYLlyDdS0=s88-c-k-c0x00ffffff-no-rj",
      "author_is_uploader": false,
      "author_is_verified": false,
      "author_url": "https://www.youtube.com/@tatiyana8934",
      "is_favorited": false,
      "is_pinned": false
    },
    {
      "id": "UgzqLxtms-wd7k5Sg7Z4AaABAg.9nPdEjDPmvv9nPdOeOcZee",
      "parent": "UgzqLxtms-wd7k5Sg7Z4AaABAg",
      "text": "...❤🙏🏻🌸",
      "author_id": "UCUv2d26BIwPdADOPWJNWtCA",
      "author": "@tatiyana8934",
      "author_thumbnail": "https://yt3.ggpht.com/ytc/AIdro_mXI8-EOUqSNpx0og7DpiBLxSD_mIUjw4493KhYLlyDdS0=s88-c-k-c0x00ffffff-no-rj",
      "author_is_uploader": false,
      "author_is_verified": false,
      "author_url": "https://www.youtube.com/@tatiyana8934",
      "is_favorited": false,
      "is_pinned": false
    }
  ]
}
