{
  "comments": [
    {
      "id": "UgwlVPMD8Z8hGqiKKdB4AaABAg",
      "parent": "root",
      "text": "ПРИГЛАШАЮТСЯ ПОМОЩНИКИ ДЛЯ НАПИСАНИЯ КОНСПЕКТА ЛЕКЦИЙ АНЧИ))\nТАЙМ-КОДЫ ПОЯВЛЯЮТСЯ ПО МЕРЕ ГОТОВНОСТИ, НО ПОСЛЕ УПОРЯДОЧЕНИЯ КОММЕНТАРИЕВ ПО \"СНАЧАЛА НОВЫЕ\"",
      "author_id": "UCdZcJ0akX0dTD9lSJTbjG_g",
      "author": "@dina-n9005",
      "author_thumbnail": "https://yt3.ggpht.com/ytc/AIdro_lGEkFpJZmZniNT5g38Bipo3CiNCqgbGo7aP1c4u0DPhiY=s88-c-k-c0x00ffffff-no-rj",
      "author_is_uploader": false,
      "author_is_verified": false,
      "author_url": "https://www.youtube.com/@dina-n9005",
      "is_favorited": false,
      "is_pinned": true
    },
    {
      "id": "UgwlVPMD8Z8hGqiKKdB4AaABAg.ABTqIhOKiCxABTqPel_4s8",
      "parent": "UgwlVPMD8Z8hGqiKKdB4AaABAg",
      "text": "ПРИГЛАШАЮТСЯ ПОМОЩНИКИ ДЛЯ НАПИСАНИЯ КОНСПЕКТА ЛЕКЦИЙ АНЧИ)",
      "author_id": "UCdZcJ0akX0dTD9lSJTbjG_g",
      "author": "@dina-n9005",
      "author_thumbnail": "https://yt3.ggpht.com/ytc/AIdro_lGEkFpJZmZniNT5g38Bipo3CiNCqgbGo7aP1c4u0DPhiY=s88-c-k-c0x00ffffff-no-rj",
      "author_is_uploader": false,
      "author_is_verified": false,
      "author_url": "https://www.youtube.com/@dina-n9005",
      "is_favorited": false,
      "is_pinned": false
    },
    {
      "id": "UgwlVPMD8Z8hGqiKKdB4AaABAg.ABTqIhOKiCxABTqQFCeOcs",
      "parent": "UgwlVPMD8Z8hGqiKKdB4AaABAg",
      "text": "00:01Привет, дорогие! Угадайте, где я)\r\n4:48 Анонс новостей\r\n5:17 Новости о лечении болезни Альцгеймера\r\n5:28 1-ая: Симуфилам провалился\r\n7:55 2-я: доставка конъюгата BCC10-олигонуклеотид\r\n12:49 1:34:31 3-я: микрохирургия в лечении БА \r\n20:06 Спрашивают про антидепрессанты\r\n21:49 О гамалеевском препарате от рака\r\n25:30 О Марти Макари и системе здравоохранения в США\r\n34:16 Треонаты и оротаты\r\n35:56 Парапробиотики – засушенные шкурки бактерий\r\n41:15 Мама в больнице!\r\n47:10 Просьба помочь каналу\r\n48:28 51:06 Еще о маме \r\n49:11 Лактобациллусы\r\n51:24 Остеопороз \r\n52:37 Мелатонин",
      "author_id": "UCdZcJ0akX0dTD9lSJTbjG_g",
      "author": "@dina-n9005",
      "author_thumbnail": "https://yt3.ggpht.com/ytc/AIdro_lGEkFpJZmZniNT5g38Bipo3CiNCqgbGo7aP1c4u0DPhiY=s88-c-k-c0x00ffffff-no-rj",
      "author_is_uploader": false,
      "author_is_verified": false,
      "author_url": "https://www.youtube.com/@dina-n9005",
      "is_favorited": false,
      "is_pinned": false
    },
    {
      "id": "UgwlVPMD8Z8hGqiKKdB4AaABAg.ABTqIhOKiCxABTqQYJYFja",
      "parent": "UgwlVPMD8Z8hGqiKKdB4AaABAg",
      "text": "00:54:41 уменьшает ли кофе всасываемость Д3, К2 и магния? (Анча: кофе уменьшает всасываемость всего)\r\n00:55:35 аналог Мезима в России\r\n00:55:58 уровень NO-синтазы после 50 лет, Виагра\r\n00:56:38 прием Амброксола сразу после Мукалтина, ребенок 6 лет\r\n00:56:51 уровень триглициридов 1.95, можно ли снизить их с помощью липотропного комплекса?\r\n00:57:37 колоноскопия с седацией или без у пациента 66 лет?\r\n00:58:36 нужно ли прерывать прием хрома пиколината через месяц, жен. 68 лет?\r\n00:59:42 способы восстановления миелина при рассеянном склерозе\r\n01:00:28 может ли Ангиовит (вит. В6, В9, В12) вызывать приливы у жен. 70 лет?\r\n01:01:19 колоноскопия только с седацией, очищение перед колоноскопией\r\n01:02:02 Креон, панкреатин\r\n01:02:20 нос закладывает уже 1 год\r\n01:03:30 слабость и низкая температура после микоплазмы в сентябре и COVID и гриппа в феврале, дев. 13 лет?\r\n01:03:50 омега-3 и аритмия\r\n01:04:40 МРТ головного мозга с контрастом и без\r\n01:05:52 снова про Мезим\r\n01:06:00 можно ли пить подростку 16 лет креатин и протеин при тренировках?\r\n01:06:32 рассеянный склероз, возбудители, профилактика натуральными противовоспалительными средствами",
      "author_id": "UCdZcJ0akX0dTD9lSJTbjG_g",
      "author": "@dina-n9005",
      "author_thumbnail": "https://yt3.ggpht.com/ytc/AIdro_lGEkFpJZmZniNT5g38Bipo3CiNCqgbGo7aP1c4u0DPhiY=s88-c-k-c0x00ffffff-no-rj",
      "author_is_uploader": false,
      "author_is_verified": false,
      "author_url": "https://www.youtube.com/@dina-n9005",
      "is_favorited": false,
      "is_pinned": false
    },
    {
      "id": "UgwlVPMD8Z8hGqiKKdB4AaABAg.ABTqIhOKiCxABTqRFlU3J0",
      "parent": "UgwlVPMD8Z8hGqiKKdB4AaABAg",
      "text": "1:07:02 Чем лечить бородавки? Удаляли, вырастают.\r\n1:07:50 В месте старого перелома на тазобедренном суставе начался артроз. Как приостановить процесс?\r\n1:08:37 При ГЭРБ хорошо ли использовать цинк L-карнитин?\r\n1:09:12 Можно ли принимать вместе K2 (МК7) и наттокиназу?\r\n1:09:41 Как укрепить гематоэнцефалический барьер? Есть ли что-то новое для лечения рассеянного склероза?\r\n1:10:26 Коэнзим Q10+пиперин будет лучше усвоен, чем без пиперина? И равен ли убихинолу?\r\n1:11:15 Обязательно ли антибиотики после установки зубного импланта?\r\n1:11:46 Какие анализы будет сдавать Анча, чтобы оценить ущерб от ковида?\r\n1:13:36 Какой кальций и в какой дозе лучше принимать при ревматоидных заболеваниях? \r\n1:14:10 Я вешу 46 кг, а муж 130. Одинаковые ли принимать дозировки магния, мелатонина и К2?\r\n1:15:15 После 7 дней приёма К2 произошло кровоизлияние в стекловидное тело. Теперь боюсь принимать витамин.\r\n1:15:46 Чем поддержать связки и сухожилия стопы? Стопа болит долго после лечения шпоры. Хондроитин поможет?\r\n1:16:59 На КТ головного мозга признаки лейкоареоза.\r\n1:18:40 Что предпринимать при антителах к TПO - 27,7? ТТГ - 1,8. Гипотиреоз, женщина 72 года. \r\n1:19:09 CoQ-10 MEGASORB от Solgar будет усваиваться?\r\n1:19:29 У меня грыжа пищевода (ГЭРБ), отказалась от Омепразола, стараюсь после еды быть в вертикальном положении (не лежать).\r\n1:19:48 Селен 0,138, какая может быть причина превышения? Витамины не принимала, креветками не злоупотребляю, как понизить? На что влияет превышение?",
      "author_id": "UCdZcJ0akX0dTD9lSJTbjG_g",
      "author": "@dina-n9005",
      "author_thumbnail": "https://yt3.ggpht.com/ytc/AIdro_lGEkFpJZmZniNT5g38Bipo3CiNCqgbGo7aP1c4u0DPhiY=s88-c-k-c0x00ffffff-no-rj",
      "author_is_uploader": false,
      "author_is_verified": false,
      "author_url": "https://www.youtube.com/@dina-n9005",
      "is_favorited": false,
      "is_pinned": false
    },
    {
      "id": "UgwlVPMD8Z8hGqiKKdB4AaABAg.ABTqIhOKiCxABTqS6ejjW6",
      "parent": "UgwlVPMD8Z8hGqiKKdB4AaABAg",
      "text": "1:20:15   боль в суставах после чрезмерного приема вит.Д3;\r\n1:21:12   слабость и температура после перенесенной микоплазмы;\r\n1:21:50   назначение омепразола при сниженной кислотности;\r\n1:23:28   про дозировки американских мультивитаминов после ковида;\r\n1:24:26   как восстановить миелин? \r\n1:24:43   при ОРЗ без температуры можно ли посетить парную?\r\n1:25:19   могут ли быть  слуховые галлюцинации  у здорового человека?\r\n1:26:13   про назначение ингибитора третьего типа;\r\n1:26:45   можно ли принимать  вит. С и рутин при повышенных оксалатах?\r\n1:27:38   про лечение шпор на пятках;\r\n1:28:13   искажение обоняния после ковида;\r\n1:28:50   как и когда принимать витамины Д и К2 с учетом кофе?\r\n1:29:24   прозак и снижение тестостерона;\r\n1:29:47   71г. , жжение кожи ног и поясницы;\r\n1:30:33   можно ли есть рыбу, сёмгу например, каждый день?\r\n1:31:58   ферритин 30 – это норм?\r\n1:32:08    лимфатический узел на фоне приема згт;\r\n1:32:53   что поможет от POTS (cиндром постуральной ортостатической тахикардии) после ковида?",
      "author_id": "UCdZcJ0akX0dTD9lSJTbjG_g",
      "author": "@dina-n9005",
      "author_thumbnail": "https://yt3.ggpht.com/ytc/AIdro_lGEkFpJZmZniNT5g38Bipo3CiNCqgbGo7aP1c4u0DPhiY=s88-c-k-c0x00ffffff-no-rj",
      "author_is_uploader": false,
      "author_is_verified": false,
      "author_url": "https://www.youtube.com/@dina-n9005",
      "is_favorited": false,
      "is_pinned": false
    },
    {
      "id": "UgwlVPMD8Z8hGqiKKdB4AaABAg.ABTqIhOKiCxABTqSgITQ6I",
      "parent": "UgwlVPMD8Z8hGqiKKdB4AaABAg",
      "text": "КРАТКО с 1:33:41 до 1:56:22\r\nКофе.Тримедат.Рыбий жир.АИТ и вес.Остеогенон.\nБАДы и витамины.Токсикоз.Fenugreek.Куркумин.\nНасморк.Геморрой.Ранки на лице.Билирубин.Сон.\nТримебутин.Викалин.Онкология.Кашель.Перелом.\nАнтиоксиданты.Медицина в США.Герпес и соль.\nВстречи.После ковида.Крапивница.Сон.",
      "author_id": "UCdZcJ0akX0dTD9lSJTbjG_g",
      "author": "@dina-n9005",
      "author_thumbnail": "https://yt3.ggpht.com/ytc/AIdro_lGEkFpJZmZniNT5g38Bipo3CiNCqgbGo7aP1c4u0DPhiY=s88-c-k-c0x00ffffff-no-rj",
      "author_is_uploader": false,
      "author_is_verified": false,
      "author_url": "https://www.youtube.com/@dina-n9005",
      "is_favorited": false,
      "is_pinned": false
    },
    {
      "id": "UgwlVPMD8Z8hGqiKKdB4AaABAg.ABTqIhOKiCxABUQKVicpJX",
      "parent": "UgwlVPMD8Z8hGqiKKdB4AaABAg",
      "text": "С 1:33:41 до 1:56:22\nКофе.Тримедат.Рыбий жир.АИТ и вес.Остеогенон.\nБАДы и витамины.Токсикоз.Fenugreek.Куркумин.\nНасморк.Геморрой.Ранки на лице.Билирубин.Сон.\nТримебутин.Викалин.Онкология.Кашель.Перелом.\nАнтиоксиданты.Медицина в США.Герпес и соль.\nВстречи.После ковида.Крапивница.Сон.",
      "author_id": "UCdZcJ0akX0dTD9lSJTbjG_g",
      "author": "@dina-n9005",
      "author_thumbnail": "https://yt3.ggpht.com/ytc/AIdro_lGEkFpJZmZniNT5g38Bipo3CiNCqgbGo7aP1c4u0DPhiY=s88-c-k-c0x00ffffff-no-rj",
      "author_is_uploader": false,
      "author_is_verified": false,
      "author_url": "https://www.youtube.com/@dina-n9005",
      "is_favorited": false,
      "is_pinned": false
    },
    {
      "id": "UgwlVPMD8Z8hGqiKKdB4AaABAg.ABTqIhOKiCxABUQKrKAD6Q",
      "parent": "UgwlVPMD8Z8hGqiKKdB4AaABAg",
      "text": "1:56:22 Связано ли понижение билирубина в анализах и исчезновение полипов в кишечнике?\r\n1:56:58 О неприятных странностях со страховыми компаниями в США \r\n1:58:42 О ситуации с запретом разглашения результатов тестов на вирусы в Нью-Йорке \r\n1:59:28 В чём причина просыпания каждый час с учащённым сердцебиением? \r\n2:00:00 Может ли быть сколиоз причиной нарушения кровотока в сосудах правой половины шеи? \r\n2:00:46 Можно ли принимать Дезлоратадин месяцами? \r\n2:01:19 Об анализе, собранном в течение пяти дней \r\n2:01:30 О затратах на пандемию в США \r\n2:02:16 Какие добавки можно принимать после операции по замене клапана сердца в 68 лет? \r\n2:03:52 Акупрессура в России как физиотерапия \r\n2:04:07 Уточнение по крапивнице у семьи \r\n2:04:32 О возвращении Анчи в Турцию \r\n2:06:55 Можно ли делать массаж воротниковой зоны при проблемах со щитовидной железой?\r\n2:07:08 Ещё раз о кислоте от крапивницы. \r\n2:07:41 Про Судафед в таблетках от насморка \r\n2:08:01 Вопрос о мази от герпеса \r\n2:08:21 Про Анчины встречи со зрителями",
      "author_id": "UCdZcJ0akX0dTD9lSJTbjG_g",
      "author": "@dina-n9005",
      "author_thumbnail": "https://yt3.ggpht.com/ytc/AIdro_lGEkFpJZmZniNT5g38Bipo3CiNCqgbGo7aP1c4u0DPhiY=s88-c-k-c0x00ffffff-no-rj",
      "author_is_uploader": false,
      "author_is_verified": false,
      "author_url": "https://www.youtube.com/@dina-n9005",
      "is_favorited": false,
      "is_pinned": false
    },
    {
      "id": "UgwlVPMD8Z8hGqiKKdB4AaABAg.ABTqIhOKiCxABUQLC5B3MI",
      "parent": "UgwlVPMD8Z8hGqiKKdB4AaABAg",
      "text": "ПРИГЛАШАЮТСЯ ПОМОЩНИКИ ДЛЯ НАПИСАНИЯ КОНСПЕКТА ЛЕКЦИЙ АНЧИ)",
      "author_id": "UCdZcJ0akX0dTD9lSJTbjG_g",
      "author": "@dina-n9005",
      "author_thumbnail": "https://yt3.ggpht.com/ytc/AIdro_lGEkFpJZmZniNT5g38Bipo3CiNCqgbGo7aP1c4u0DPhiY=s88-c-k-c0x00ffffff-no-rj",
      "author_is_uploader": false,
      "author_is_verified": false,
      "author_url": "https://www.youtube.com/@dina-n9005",
      "is_favorited": false,
      "is_pinned": false
    },
    {
      "id": "UgwlVPMD8Z8hGqiKKdB4AaABAg.ABTqIhOKiCxABVe4a_3kM3",
      "parent": "UgwlVPMD8Z8hGqiKKdB4AaABAg",
      "text": "1:07:02 Чем лечить бородавки? Удаляли, вырастают.\n1:07:50 В месте старого перелома на тазобедренном суставе начался артроз. Как приостановить процесс?\n1:08:37 При ГЭРБ хорошо ли использовать цинк Л-карнитин?\n1:09:12 Можно ли принимать вместе K2 (МК7) и наттокиназу?\n1:09:41 Как укрепить гематоэнцефалический барьер? Есть ли что-то новое для лечения рассеянного склероза?\n1:10:26 Коэнзим Q10+пиперин будет лучше усвоен, чем без пиперина? И равен ли убихинолу?\n1:11:15 Обязательно ли антибиотики после установки зубного импланта?\n1:11:46 Какие анализы будет сдавать Анча, чтобы оценить ущерб от ковида?\n1:13:36 Какой кальций и в какой дозе лучше принимать при ревматоидных заболеваниях? \n1:14:10 Я вешу 46 кг, а муж 130. Одинаковые ли принимать дозировки магния, мелатонина и К2?\n1:15:15 После 7 дней приёма К2 произошло кровоизлияние в стекловидное тело. Теперь боюсь принимать витамин.\n1:15:46 Чем поддержать связки и сухожилия стопы? Стопа болит долго после лечения шпоры. Хондроитин поможет?\n1:16:59 На КТ головного мозга признаки лейкоареоза.\n1:18:40 Что предпринимать при антителах к TPO - 27,7? ТТГ - 1,8. Гипотиреоз, женщина 72 года. \n1:19:09 CoQ-10 MEGASORB от Solgar будет усваиваться?\n1:19:29 Уу меня грыжа пищевода (ГЭРБ), отказалась от Омепразола, стараюсь после еды быть в вертикальном положении (не лежать).\n1:19:48 Селен 0,138, какая может быть причина превышения? Витамины не принимала, креветками не злоупотребляю, как понизить? На что влияет превышение?",
      "author_id": "UCWi1Qms79_mvWJPGxuCuGkQ",
      "author": "@nadiadja",
      "author_thumbnail": "https://yt3.ggpht.com/ytc/AIdro_lA5uL_95A09Jr3R5DBr2jgqlc3skSu6sM12D1kuEEZLZQ=s88-c-k-c0x00ffffff-no-rj",
      "author_is_uploader": false,
      "author_is_verified": false,
      "author_url": "https://www.youtube.com/@nadiadja",
      "is_favorited": false,
      "is_pinned": false
    },
    {
      "id": "UgwlVPMD8Z8hGqiKKdB4AaABAg.ABTqIhOKiCxABWYAogY8pK",
      "parent": "UgwlVPMD8Z8hGqiKKdB4AaABAg",
      "text": "1:20:15   боль в суставах после чрезмерного приема вит.Д3;\r\n1:21:12   слабость и температура после перенесенной микоплазмы;\r\n1:21:50   назначение омепразола при сниженной кислотности;\r\n1:23:28   про дозировки американских мультивитамин после ковида;\r\n1:24:26   как восстановить миелин? \r\n1:24:43   при ОРЗ без температуры можно ли посетить парную?\r\n1:25:19   могут ли быть  слуховые галлюцинации  у здорового человека?\r\n1:26:13   про назначение ингибитора третьего типа;\r\n1:26:45   можно ли принимать  вит. С и рутин при повышенных оксалатах?\r\n1:27:38   про лечение шпор на пятках;\r\n1:28:13   искажение обоняния после ковида;\r\n1:28:50   как и когда принимать витамины Д и К2 с учетом кофе?\r\n1:29:24   прозак и снижение тестостерона;\r\n1:29:47   71г. , жжение кожи ног и поясницы;\r\n1:30:33   можно ли есть рыбу, сёмгу например, каждый день?\r\n1:31:58   ферритин 30 – это норм?\r\n1:32:08    лимфатический узел на фоне приема згт;\r\n1:32:53   что поможет от потца после ковида?",
      "author_id": "UCrc3qb__6_tSdTU6sM6IxYw",
      "author": "@Алла-б1ъ4д",
      "author_thumbnail": "https://yt3.ggpht.com/ytc/AIdro_mz4b6tJ6995w5bXockbkWuHK12DEoVSMROuK1MkCdeJ_I=s88-c-k-c0x00ffffff-no-rj",
      "author_is_uploader": false,
      "author_is_verified": false,
      "author_url": "https://www.youtube.com/@%D0%90%D0%BB%D0%BB%D0%B0-%D0%B11%D1%8A4%D0%B4",
      "is_favorited": false,
      "is_pinned": false
    },
    {
      "id": "UgwlVPMD8Z8hGqiKKdB4AaABAg.ABTqIhOKiCxABXgA7atFEL",
      "parent": "UgwlVPMD8Z8hGqiKKdB4AaABAg",
      "text": "С 1:33:41 до 1:56:22 (очень кратко):\r\nКофе.Тримедат.Рыбий жир.\nАИТ и вес.Остеогенон.\nБАДы и витамины.Токсикоз.\nFenugreek.Куркумин.Насморк.\nГеморрой.Ранки на лице.Билирубин\nСон.Тримебутин.Викалин.Онкология.\nКашель.Перелом.Антиоксиданты.\nМедицина в США.Герпес и соль.Встречи.\nПосле ковида.Крапивница.Сон.",
      "author_id": "UCdZcJ0akX0dTD9lSJTbjG_g",
      "author": "@dina-n9005",
      "author_thumbnail": "https://yt3.ggpht.com/ytc/AIdro_lGEkFpJZmZniNT5g38Bipo3CiNCqgbGo7aP1c4u0DPhiY=s88-c-k-c0x00ffffff-no-rj",
      "author_is_uploader": false,
      "author_is_verified": false,
      "author_url": "https://www.youtube.com/@dina-n9005",
      "is_favorited": false,
      "is_pinned": false
    },
    {
      "id": "UgwlVPMD8Z8hGqiKKdB4AaABAg.ABTqIhOKiCxABXpAmFuEID",
      "parent": "UgwlVPMD8Z8hGqiKKdB4AaABAg.ABTqIhOKiCxABTqQFCeOcs",
      "text": "​ @dina-n9005 спасибо!😂",
      "author_id": "UCUsRTBSsU3BkAKs8t4eQ92Q",
      "author": "@streamlinklaw",
      "author_thumbnail": "https://yt3.ggpht.com/ytc/AIdro_mm89LyPguoCp8YZIjoE7fVA8Zj3ahrenllJaITNks=s88-c-k-c0x00ffffff-no-rj",
      "author_is_uploader": false,
      "author_is_verified": false,
      "author_url": "https://www.youtube.com/@streamlinklaw",
      "is_favorited": false,
      "is_pinned": false
    },
    {
      "id": "UgwlVPMD8Z8hGqiKKdB4AaABAg.ABTqIhOKiCxABXpDBeeFn6",
      "parent": "UgwlVPMD8Z8hGqiKKdB4AaABAg.ABTqIhOKiCxABVe4a_3kM3",
      "text": "​ @nadiadja спасибо ❤",
      "author_id": "UCUsRTBSsU3BkAKs8t4eQ92Q",
      "author": "@streamlinklaw",
      "author_thumbnail": "https://yt3.ggpht.com/ytc/AIdro_mm89LyPguoCp8YZIjoE7fVA8Zj3ahrenllJaITNks=s88-c-k-c0x00ffffff-no-rj",
      "author_is_uploader": false,
      "author_is_verified": false,
      "author_url": "https://www.youtube.com/@streamlinklaw",
      "is_favorited": false,
      "is_pinned": false
    },
    {
      "id": "UgwlVPMD8Z8hGqiKKdB4AaABAg.ABTqIhOKiCxABXpEWgr-LY",
      "parent": "UgwlVPMD8Z8hGqiKKdB4AaABAg.ABTqIhOKiCxABWYAogY8pK",
      "text": "​ @Алла-б1ъ4д спасибо ❤",
      "author_id": "UCUsRTBSsU3BkAKs8t4eQ92Q",
      "author": "@streamlinklaw",
      "author_thumbnail": "https://yt3.ggpht.com/ytc/AIdro_mm89LyPguoCp8YZIjoE7fVA8Zj3ahrenllJaITNks=s88-c-k-c0x00ffffff-no-rj",
      "author_is_uploader": false,
      "author_is_verified": false,
      "author_url": "https://www.youtube.com/@streamlinklaw",
      "is_favorited": false,
      "is_pinned": false
    },
    {
      "id": "UgwlVPMD8Z8hGqiKKdB4AaABAg.ABTqIhOKiCxABXpG5dUQTZ",
      "parent": "UgwlVPMD8Z8hGqiKKdB4AaABAg.ABTqIhOKiCxABXgA7atFEL",
      "text": "​ @dina-n9005 спасибо ❤",
      "author_id": "UCUsRTBSsU3BkAKs8t4eQ92Q",
      "author": "@streamlinklaw",
      "author_thumbnail": "https://yt3.ggpht.com/ytc/AIdro_mm89LyPguoCp8YZIjoE7fVA8Zj3ahrenllJaITNks=s88-c-k-c0x00ffffff-no-rj",
      "author_is_uploader": false,
      "author_is_verified": false,
      "author_url": "https://www.youtube.com/@streamlinklaw",
      "is_favorited": false,
      "is_pinned": false
    },
    {
      "id": "UgwlVPMD8Z8hGqiKKdB4AaABAg.ABTqIhOKiCxABYVMnWQ6B8",
      "parent": "UgwlVPMD8Z8hGqiKKdB4AaABAg",
      "text": "00:54:41 уменьшает ли кофе всасываемость Д3, К2 и магния? (Анча: кофе уменьшает всасываемость всего)\n00:55:35 аналог Мезима в России\n00:55:58 уровень NO-синтазы после 50 лет, Виагра\n00:56:38 прием Амброксола сразу после Мукалтина, ребенок 6 лет\n00:56:51 уровень триглициридов 1.95, можно ли снизить их с помощью липотропного комплекса?\n00:57:37 колоноскопия с седацией или без у пациента 66 лет?\n00:58:36 нужно ли прерывать прием хрома пиколината через месяц, жен. 68 лет?\n00:59:42 способы восстановления миелина при рассеянном склерозе\n01:00:28 может ли Ангиовит (вит. В6, В9, В12) вызывать приливы у жен. 70 лет?\n01:01:19 колоноскопия только с седацией, очищение перед колоноскопией\n01:02:02 Креон, панкреатин\n01:02:20 нос закладывает уже 1 год\n01:03:30 слабость и низкая температура после микоплазмы в сентябре и COVID и гриппа в феврале, дев. 13 лет?\n01:03:50 омега-3 и аритмия\n01:04:40 МРТ головного мозга с контрастом и без\n01:05:52 снова про Мезим\n01:06:00 можно ли пить подростку 16 лет креатин и протеин при тренировках?\n01:06:32 рассеянный склероз, возбудители, профилактика натуральными противовоспалительными средствами",
      "author_id": "UCZQEWwlDyk0rnQAful__6KA",
      "author": "@annareznikova7373",
      "author_thumbnail": "https://yt3.ggpht.com/ytc/AIdro_l5abq6huSASf1Fa-88GxqMCoa5qn3MJsPp08KsYX6UXK4=s88-c-k-c0x00ffffff-no-rj",
      "author_is_uploader": false,
      "author_is_verified": false,
      "author_url": "https://www.youtube.com/@annareznikova7373",
      "is_favorited": false,
      "is_pinned": false
    },
    {
      "id": "UgwlVPMD8Z8hGqiKKdB4AaABAg.ABTqIhOKiCxABYVOXNicZL",
      "parent": "UgwlVPMD8Z8hGqiKKdB4AaABAg",
      "text": "00:54:41 уменьшает ли кофе всасываемость Д3, К2 и магния? (Анча: кофе уменьшает всасываемость всего)\n00:55:35 аналог Мезима в России\n00:55:58 уровень NO-синтазы после 50 лет, Виагра\n00:56:38 прием Амброксола сразу после Мукалтина, ребенок 6 лет\n00:56:51 уровень триглициридов 1.95, можно ли снизить их с помощью липотропного комплекса?\n00:57:37 колоноскопия с седацией или без у пациента 66 лет?\n00:58:36 нужно ли прерывать прием хрома пиколината через месяц, жен. 68 лет?\n00:59:42 способы восстановления миелина при рассеянном склерозе\n01:00:28 может ли Ангиовит (вит. В6, В9, В12) вызывать приливы у жен. 70 лет?\n01:01:19 колоноскопия только с седацией, очищение перед колоноскопией\n01:02:02 Креон, панкреатин\n01:02:20 нос закладывает уже 1 год\n01:03:30 слабость и низкая температура после микоплазмы в сентябре и COVID и гриппа в феврале, дев. 13 лет?\n01:03:50 омега-3 и аритмия\n01:04:40 МРТ головного мозга с контрастом и без\n01:05:52 снова про Мезим\n01:06:00 можно ли пить подростку 16 лет креатин и протеин при тренировках?\n01:06:32 рассеянный склероз, возбудители, профилактика натуральными противовоспалительными средствами",
      "author_id": "UCZQEWwlDyk0rnQAful__6KA",
      "author": "@annareznikova7373",
      "author_thumbnail": "https://yt3.ggpht.com/ytc/AIdro_l5abq6huSASf1Fa-88GxqMCoa5qn3MJsPp08KsYX6UXK4=s88-c-k-c0x00ffffff-no-rj",
      "author_is_uploader": false,
      "author_is_verified": false,
      "author_url": "https://www.youtube.com/@annareznikova7373",
      "is_favorited": false,
      "is_pinned": false
    }
  ]
}
